LICENSE
MANIFEST.in
README.md
README.rst
gradle.properties
setup.cfg
setup.py
proactive/ProactiveBuilder.py
proactive/ProactiveFactory.py
proactive/ProactiveGateway.py
proactive/ProactiveRestApi.py
proactive/ProactiveUtils.py
proactive/__init__.py
proactive/logging.conf
proactive.egg-info/PKG-INFO
proactive.egg-info/SOURCES.txt
proactive.egg-info/dependency_links.txt
proactive.egg-info/not-zip-safe
proactive.egg-info/requires.txt
proactive.egg-info/top_level.txt
proactive/java/log4j.properties
proactive/java/lib/FastInfoset-1.2.12.jar
proactive/java/lib/activation-1.1.1.jar
proactive/java/lib/apache-log4j-extras-1.2.17.jar
proactive/java/lib/apache-mime4j-0.6.jar
proactive/java/lib/async-http-client-1.9.20.jar
proactive/java/lib/common-api-13.0.1.jar
proactive/java/lib/common-http-13.0.1.jar
proactive/java/lib/commons-cli-1.3.1.jar
proactive/java/lib/commons-codec-1.11.jar
proactive/java/lib/commons-collections4-4.4.jar
proactive/java/lib/commons-io-2.5.jar
proactive/java/lib/commons-lang3-3.5.jar
proactive/java/lib/commons-logging-1.2.jar
proactive/java/lib/commons-vfs2-2.7.0.jar
proactive/java/lib/cron4j-2.2.5.jar
proactive/java/lib/guava-19.0.jar
proactive/java/lib/httpclient-4.5.13.jar
proactive/java/lib/httpcore-4.4.13.jar
proactive/java/lib/httpmime-4.5.13.jar
proactive/java/lib/isorelax-20050913.jar
proactive/java/lib/istack-commons-runtime-2.16.jar
proactive/java/lib/jackson-core-asl-1.9.13.jar
proactive/java/lib/jackson-jaxrs-1.9.13.jar
proactive/java/lib/jackson-mapper-asl-1.9.13.jar
proactive/java/lib/jackson-xc-1.9.13.jar
proactive/java/lib/jasypt-1.9.3.jar
proactive/java/lib/javax.mail-1.5.6.jar
proactive/java/lib/jaxb-api-2.2.7.jar
proactive/java/lib/jaxb-core-2.2.7.jar
proactive/java/lib/jaxb-impl-2.2.7.jar
proactive/java/lib/jboss-annotations-api_1.2_spec-1.0.0.Final.jar
proactive/java/lib/jboss-jaxrs-api_2.0_spec-1.0.1.Beta1.jar
proactive/java/lib/jboss-logging-3.3.0.Final.jar
proactive/java/lib/jcip-annotations-1.0.jar
proactive/java/lib/jdbm-2.0.1.jar
proactive/java/lib/jline-2.14.2.jar
proactive/java/lib/jna-4.1.0.jar
proactive/java/lib/joda-time-2.9.1.jar
proactive/java/lib/json-simple-1.1.jar
proactive/java/lib/jsr173_api-1.0.jar
