Metadata-Version: 2.1
Name: proactive
Version: 13.0.1
Summary: ProActive scheduler client module
Home-page: https://github.com/ow2-proactive/proactive-python-client
Author: Activeeon
Author-email: contact@activeeon.com
License: Apache-2.0
Platform: UNKNOWN
Requires-Python: >=2.7
